LICENSE
README.md
make_agents/__init__.py
make_agents/bonus.py
make_agents/gpt.py
make_agents/make_agents.py
make_agents-0.2.1.dist-info/LICENSE
make_agents-0.2.1.dist-info/METADATA
make_agents-0.2.1.dist-info/WHEEL
make_agents-0.2.1.dist-info/RECORD
