Metadata-Version: 2.1
Name: make_agents
Version: 0.2.1
Summary: 
Home-page: https://github.com/sradc/make_agents
License: Apache-2.0
Author: sradc
Author-email: sidneyradcliffe@sky.com
Requires-Python: >=3.9,<3.13
Classifier: License :: OSI Approved :: Apache Software License
Classifier: Programming Language :: Python :: 3
Classifier: Programming Language :: Python :: 3.9
Classifier: Programming Language :: Python :: 3.10
Classifier: Programming Language :: Python :: 3.11
Requires-Dist: importlib-metadata (>=6.8.0,<7.0.0)
Requires-Dist: openai (>=0.28.1,<0.29.0)
Requires-Dist: pydantic (>=2.4.2,<3.0.0)
Requires-Dist: tenacity (>=8.2.3,<9.0.0)
Project-URL: Repository, https://github.com/sradc/make_agents
